{
    "isAuthorized": true,
    "communityName": "State of Georgia Roleplay",
    "communityAbbreviation": "SOGRP",
    "zones": [
        { "zoneid": 1, "zonetag": "Z1 Main" },
        { "zoneid": 2, "zonetag": "Z2 GSP LAW" },
        { "zoneid": 3, "zonetag": "Z3 GWINNETT LAW" },
        { "zoneid": 4, "zonetag": "Z4 APD LAW" }
    ],
    "talkgroups": [
        { "znid": 1, "name": "GSP Statewide", "tgid": 101, "convectional": false, "secure": true, "encryptionKey": "", "announce": "GSP Statewide" },
        { "znid": 1, "name": "GCSO Disp", "tgid": 107, "convectional": false, "secure": true, "encryptionKey": "", "announce": "Gwinnett Dispatch" },
        { "znid": 1, "name": "APD Z1 Disp", "tgid": 112, "convectional": false, "secure": true, "encryptionKey": "", "announce": "Atlanta Zone 1 Dispatch" },
        { "znid": 1, "name": "GCFES Disp", "tgid": 116, "convectional": false, "secure": true, "encryptionKey": "", "announce": "Fire Dispatch" },

        { "znid": 2, "name": "GSP Statewide", "tgid": 101, "convectional": false, "secure": true, "encryptionKey": "", "announce": "GSP Statewide" },
        { "znid": 2, "name": "GSP C Dispatch", "tgid": 102, "convectional": false, "secure": false, "encryptionKey": "", "announce": "GSP County" },
        { "znid": 2, "name": "GSP M Dispatch", "tgid": 103, "convectional": false, "secure": false, "encryptionKey": "", "announce": "GSP Metro" },
        { "znid": 2, "name": "GSP Command", "tgid": 104, "convectional": false, "secure": false, "encryptionKey": "", "announce": "GSP Command" },
        { "znid": 2, "name": "GSP Car-Car", "tgid": 105, "convectional": false, "secure": true, "encryptionKey": "", "announce": "GSP Car-to-Car" },
        { "znid": 2, "name": "GSP Tac 1A", "tgid": 106, "convectional": false, "secure": true, "encryptionKey": "", "announce": "GSP Tactical 1" },

        { "znid": 3, "name": "GCSO Disp", "tgid": 107, "secure": true, "encryptionKey": "", "announce": "Gwinnett Dispatch" },
        { "znid": 3, "name": "GCSO Alt", "tgid": 108, "secure": false, "encryptionKey": "", "announce": "Gwinnett Alternate" },
        { "znid": 3, "name": "GCSO Supv", "tgid": 109, "secure": false, "encryptionKey": "", "announce": "Gwinnett Supervisord" },
        { "znid": 3, "name": "GCSO Tac 1B", "tgid": 110, "secure": true, "encryptionKey": "", "announce": "Gwinnett Tact 1" },
        { "znid": 3, "name": "GCSO Tac 2C", "tgid": 111, "secure": true, "encryptionKey": "", "announce": "Gwinnett Tact 2" },

        { "znid": 4, "name": "APD Z4 Disp", "tgid": 112, "convectional": false, "secure": true, "encryptionKey": "", "announce": "Zone 4 Dispatch" },
        { "znid": 4, "name": "APD Z4 Supv", "tgid": 113, "convectional": false, "secure": true, "encryptionKey": "", "announce": "Zone 4 Supervisor" },
        { "znid": 4, "name": "APD Tac-1D", "tgid": 114, "convectional": false, "secure": true, "encryptionKey": "", "announce": "APD Tactical 1" },
        { "znid": 4, "name": "APD Events 1", "tgid": 115, "convectional": false, "secure": true, "encryptionKey": "", "announce": "APD Events" }
    ],
    "tones": [
        { "id": 1, "name": "Advanced Life Support", "freqA": 110, "freqB": 220 },
        { "id": 2, "name": "Basic Life Support", "freqA": 110, "freqB": 220 },
        { "id": 3, "name": "Structure Fire Residential", "freqA": 110, "freqB": 220 },
        { "id": 4, "name": "Structure Fire Commercial", "freqA": 110, "freqB": 220 },
        { "id": 5, "name": "Major Incident", "freqA": 110, "freqB": 220 },
        { "id": 6, "name": "Special Incident HR/AL", "freqA": 110, "freqB": 220 },
        { "id": 7, "name": "Misc. Advisory Tone (V-A-C)", "freqA": 110, "freqB": 220 },
        { "id": 8, "name": "Mayday Air Traffic Incident", "freqA": 110, "freqB": 220 }
    ]
}
